Workbook

Sheet Devis
A1: Raison sociale | F1: DEVIS | L1: PARAMÈTRES
A2: Adresse | F2: N° de devis | H2: DEV-2026-001 | L2: Taux de TVA | N2: 0.2
A3: Code postal – Ville | F3: Date | H3: 46316 | L3: Autoliquidation TVA | N3: Non
A4: SIRET : | F4: Validité (jours) | H4: 30
A5: N° TVA intracommunautaire : | F5: Valable jusqu'au | H5: =IF(OR(H3="",H4=""),"",H3+H4) -> 46346
A6: Tél. : E-mail : | F6: Réf. client / commande | L6: COMMENT REMPLIR
L7: • Cases jaunes = à remplir. Tout le reste se calcule.
A8: CLIENT | C8: CHANTIER | L8: • Prestation : choisir dans la liste (code · désignation). Unité et prix viennent de l'onglet BPU.
A9: Société | C9: Projet / réseau | D9: Moselle Fibre – RHD57 | L9: • Qté : en ml, unités, heures, fibres… selon l'unité affichée.
A10: Contact | C10: Objet | D10: Exemple : raccordements, SAV et pose de câble (à remplacer) | L10: • PU HT sur devis : seulement pour les lignes « Sur devis » (case orange) ou pour forcer un prix.
A11: Adresse | C11: Site / commune | L11: • Majoration : MC-07 (technicien supplémentaire) ou MC-08 (HNO) multiplie le montant de la ligne par le coefficient du BPU (onglet Majorations).
A12: Code postal – Ville | C12: Base de prix | D12: BPU Moselle Fibre – RHD57 (Maintenance et VDR Optique) | L12: • Les 6 lignes remplies sont un exemple : effacer les colonnes Prestation, Qté et Majoration.
L13: • 30 lignes prévues. Pour en ajouter : insérer des lignes au milieu du tableau, puis recopier une ligne remplie vers le bas.
A14: N° | B14: Prestation (code · désignation BPU) | C14: Unité | D14: Qté | E14: PU HT BPU | F14: PU HT sur devis | G14: Majoration | H14: Montant HT | J14: lig | K14: prix | L14: • Seules les colonnes A à H s'impriment (paysage, une page de large).
A15: =IF($B15="","",COUNTA($B$15:$B15)) -> 1 | B15: RA-F1 · Raccordement abonné Opera Pro (PM) | C15: =IF(OR($J15="",$J15=0),"",INDEX(BPU!$G$2:$G$117,$J15)&"") -> Forfait par opération | D15: 2 | E15: =IF($B15="","",IF($J15=0,"Hors BPU",IF(ISNUMBER($K15),ROUND($K15,2),$K15))) -> 210 | H15: =IF($B15="","",IF(AND($F15="",NOT(ISNUMBER($E15))),"PU à saisir",ROUND(N($D15)*IF($F15<>"",$F15,$E15)*IF($G15="",1,IFERROR(INDEX(Majorations!$C$2:$C$3,MATCH($G15,ListeMajorations,0)),1)),2))) -> 420 | J15: =IF($B15="","",IFERROR(MATCH($B15,ListePrestations,0),0)) -> 1 | K15: =IF(OR($J15="",$J15=0),"",INDEX(BPU!$H$2:$H$117,$J15)) -> 210
A16: =IF($B16="","",COUNTA($B$15:$B16)) -> 2 | B16: MC-01 · Intervention Immédiate en HO TELECOM - opérations sur equipement actif | C16: =IF(OR($J16="",$J16=0),"",INDEX(BPU!$G$2:$G$117,$J16)&"") -> Forfait par intervention | D16: 1 | E16: =IF($B16="","",IF($J16=0,"Hors BPU",IF(ISNUMBER($K16),ROUND($K16,2),$K16))) -> 160.34 | G16: MC-08 · Intervention en HNO | H16: =IF($B16="","",IF(AND($F16="",NOT(ISNUMBER($E16))),"PU à saisir",ROUND(N($D16)*IF($F16<>"",$F16,$E16)*IF($G16="",1,IFERROR(INDEX(Majorations!$C$2:$C$3,MATCH($G16,ListeMajorations,0)),1)),2))) -> 225.73 | J16: =IF($B16="","",IFERROR(MATCH($B16,ListePrestations,0),0)) -> 16 | K16: =IF(OR($J16="",$J16=0),"",INDEX(BPU!$H$2:$H$117,$J16)) -> 160.34179
A17: =IF($B17="","",COUNTA($B$15:$B17)) -> 3 | B17: MC-T1 · Heure de technicien équipé en HO (8h00 – 18h00) - Intervention Immédiate | C17: =IF(OR($J17="",$J17=0),"",INDEX(BPU!$G$2:$G$117,$J17)&"") -> Forfait par heure | D17: 3 | E17: =IF($B17="","",IF($J17=0,"Hors BPU",IF(ISNUMBER($K17),ROUND($K17,2),$K17))) -> 35.93 | H17: =IF($B17="","",IF(AND($F17="",NOT(ISNUMBER($E17))),"PU à saisir",ROUND(N($D17)*IF($F17<>"",$F17,$E17)*IF($G17="",1,IFERROR(INDEX(Majorations!$C$2:$C$3,MATCH($G17,ListeMajorations,0)),1)),2))) -> 107.79 | J17: =IF($B17="","",IFERROR(MATCH($B17,ListePrestations,0),0)) -> 24 | K17: =IF(OR($J17="",$J17=0),"",INDEX(BPU!$H$2:$H$117,$J17)) -> 35.92625
A18: =IF($B18="","",COUNTA($B$15:$B18)) -> 4 | B18: 4.1.1 · Pose de câbles à fibres optiques, G657-A2 ou G652-D , de 1 FO à 144 FO | C18: =IF(OR($J18="",$J18=0),"",INDEX(BPU!$G$2:$G$117,$J18)&"") -> ml | D18: 250 | E18: =IF($B18="","",IF($J18=0,"Hors BPU",IF(ISNUMBER($K18),ROUND($K18,2),$K18))) -> 1 | H18: =IF($B18="","",IF(AND($F18="",NOT(ISNUMBER($E18))),"PU à saisir",ROUND(N($D18)*IF($F18<>"",$F18,$E18)*IF($G18="",1,IFERROR(INDEX(Majorations!$C$2:$C$3,MATCH($G18,ListeMajorations,0)),1)),2))) -> 250 | J18: =IF($B18="","",IFERROR(MATCH($B18,ListePrestations,0),0)) -> 40 | K18: =IF(OR($J18="",$J18=0),"",INDEX(BPU!$H$2:$H$117,$J18)) -> 1
A19: =IF($B19="","",COUNTA($B$15:$B19)) -> 5 | B19: 4.3.2 · Pose boitier pour protection d'épissure, capacité jusqu'à 24 épissures | C19: =IF(OR($J19="",$J19=0),"",INDEX(BPU!$G$2:$G$117,$J19)&"") -> u | D19: 1 | E19: =IF($B19="","",IF($J19=0,"Hors BPU",IF(ISNUMBER($K19),ROUND($K19,2),$K19))) -> 130 | H19: =IF($B19="","",IF(AND($F19="",NOT(ISNUMBER($E19))),"PU à saisir",ROUND(N($D19)*IF($F19<>"",$F19,$E19)*IF($G19="",1,IFERROR(INDEX(Majorations!$C$2:$C$3,MATCH($G19,ListeMajorations,0)),1)),2))) -> 130 | J19: =IF($B19="","",IFERROR(MATCH($B19,ListePrestations,0),0)) -> 51 | K19: =IF(OR($J19="",$J19=0),"",INDEX(BPU!$H$2:$H$117,$J19)) -> 130
A20: =IF($B20="","",COUNTA($B$15:$B20)) -> 6 | B20: 4.8.1 · Raccordement par fibre sur câble optique inférieur ou égal à 24FO | C20: =IF(OR($J20="",$J20=0),"",INDEX(BPU!$G$2:$G$117,$J20)&"") -> u (à la fibre) | D20: 24 | E20: =IF($B20="","",IF($J20=0,"Hors BPU",IF(ISNUMBER($K20),ROUND($K20,2),$K20))) -> 4.5 | H20: =IF($B20="","",IF(AND($F20="",NOT(ISNUMBER($E20))),"PU à saisir",ROUND(N($D20)*IF($F20<>"",$F20,$E20)*IF($G20="",1,IFERROR(INDEX(Majorations!$C$2:$C$3,MATCH($G20,ListeMajorations,0)),1)),2))) -> 108 | J20: =IF($B20="","",IFERROR(MATCH($B20,ListePrestations,0),0)) -> 91 | K20: =IF(OR($J20="",$J20=0),"",INDEX(BPU!$H$2:$H$117,$J20)) -> 4.5
A21: =IF($B21="","",COUNTA($B$15:$B21)) | C21: =IF(OR($J21="",$J21=0),"",INDEX(BPU!$G$2:$G$117,$J21)&"") | E21: =IF($B21="","",IF($J21=0,"Hors BPU",IF(ISNUMBER($K21),ROUND($K21,2),$K21))) | H21: =IF($B21="","",IF(AND($F21="",NOT(ISNUMBER($E21))),"PU à saisir",ROUND(N($D21)*IF($F21<>"",$F21,$E21)*IF($G21="",1,IFERROR(INDEX(Majorations!$C$2:$C$3,MATCH($G21,ListeMajorations,0)),1)),2))) | J21: =IF($B21="","",IFERROR(MATCH($B21,ListePrestations,0),0)) | K21: =IF(OR($J21="",$J21=0),"",INDEX(BPU!$H$2:$H$117,$J21))
A22: =IF($B22="","",COUNTA($B$15:$B22)) | C22: =IF(OR($J22="",$J22=0),"",INDEX(BPU!$G$2:$G$117,$J22)&"") | E22: =IF($B22="","",IF($J22=0,"Hors BPU",IF(ISNUMBER($K22),ROUND($K22,2),$K22))) | H22: =IF($B22="","",IF(AND($F22="",NOT(ISNUMBER($E22))),"PU à saisir",ROUND(N($D22)*IF($F22<>"",$F22,$E22)*IF($G22="",1,IFERROR(INDEX(Majorations!$C$2:$C$3,MATCH($G22,ListeMajorations,0)),1)),2))) | J22: =IF($B22="","",IFERROR(MATCH($B22,ListePrestations,0),0)) | K22: =IF(OR($J22="",$J22=0),"",INDEX(BPU!$H$2:$H$117,$J22))
A23: =IF($B23="","",COUNTA($B$15:$B23)) | C23: =IF(OR($J23="",$J23=0),"",INDEX(BPU!$G$2:$G$117,$J23)&"") | E23: =IF($B23="","",IF($J23=0,"Hors BPU",IF(ISNUMBER($K23),ROUND($K23,2),$K23))) | H23: =IF($B23="","",IF(AND($F23="",NOT(ISNUMBER($E23))),"PU à saisir",ROUND(N($D23)*IF($F23<>"",$F23,$E23)*IF($G23="",1,IFERROR(INDEX(Majorations!$C$2:$C$3,MATCH($G23,ListeMajorations,0)),1)),2))) | J23: =IF($B23="","",IFERROR(MATCH($B23,ListePrestations,0),0)) | K23: =IF(OR($J23="",$J23=0),"",INDEX(BPU!$H$2:$H$117,$J23))
A24: =IF($B24="","",COUNTA($B$15:$B24)) | C24: =IF(OR($J24="",$J24=0),"",INDEX(BPU!$G$2:$G$117,$J24)&"") | E24: =IF($B24="","",IF($J24=0,"Hors BPU",IF(ISNUMBER($K24),ROUND($K24,2),$K24))) | H24: =IF($B24="","",IF(AND($F24="",NOT(ISNUMBER($E24))),"PU à saisir",ROUND(N($D24)*IF($F24<>"",$F24,$E24)*IF($G24="",1,IFERROR(INDEX(Majorations!$C$2:$C$3,MATCH($G24,ListeMajorations,0)),1)),2))) | J24: =IF($B24="","",IFERROR(MATCH($B24,ListePrestations,0),0)) | K24: =IF(OR($J24="",$J24=0),"",INDEX(BPU!$H$2:$H$117,$J24))
A25: =IF($B25="","",COUNTA($B$15:$B25)) | C25: =IF(OR($J25="",$J25=0),"",INDEX(BPU!$G$2:$G$117,$J25)&"") | E25: =IF($B25="","",IF($J25=0,"Hors BPU",IF(ISNUMBER($K25),ROUND($K25,2),$K25))) | H25: =IF($B25="","",IF(AND($F25="",NOT(ISNUMBER($E25))),"PU à saisir",ROUND(N($D25)*IF($F25<>"",$F25,$E25)*IF($G25="",1,IFERROR(INDEX(Majorations!$C$2:$C$3,MATCH($G25,ListeMajorations,0)),1)),2))) | J25: =IF($B25="","",IFERROR(MATCH($B25,ListePrestations,0),0)) | K25: =IF(OR($J25="",$J25=0),"",INDEX(BPU!$H$2:$H$117,$J25))
A26: =IF($B26="","",COUNTA($B$15:$B26)) | C26: =IF(OR($J26="",$J26=0),"",INDEX(BPU!$G$2:$G$117,$J26)&"") | E26: =IF($B26="","",IF($J26=0,"Hors BPU",IF(ISNUMBER($K26),ROUND($K26,2),$K26))) | H26: =IF($B26="","",IF(AND($F26="",NOT(ISNUMBER($E26))),"PU à saisir",ROUND(N($D26)*IF($F26<>"",$F26,$E26)*IF($G26="",1,IFERROR(INDEX(Majorations!$C$2:$C$3,MATCH($G26,ListeMajorations,0)),1)),2))) | J26: =IF($B26="","",IFERROR(MATCH($B26,ListePrestations,0),0)) | K26: =IF(OR($J26="",$J26=0),"",INDEX(BPU!$H$2:$H$117,$J26))
A27: =IF($B27="","",COUNTA($B$15:$B27)) | C27: =IF(OR($J27="",$J27=0),"",INDEX(BPU!$G$2:$G$117,$J27)&"") | E27: =IF($B27="","",IF($J27=0,"Hors BPU",IF(ISNUMBER($K27),ROUND($K27,2),$K27))) | H27: =IF($B27="","",IF(AND($F27="",NOT(ISNUMBER($E27))),"PU à saisir",ROUND(N($D27)*IF($F27<>"",$F27,$E27)*IF($G27="",1,IFERROR(INDEX(Majorations!$C$2:$C$3,MATCH($G27,ListeMajorations,0)),1)),2))) | J27: =IF($B27="","",IFERROR(MATCH($B27,ListePrestations,0),0)) | K27: =IF(OR($J27="",$J27=0),"",INDEX(BPU!$H$2:$H$117,$J27))
A28: =IF($B28="","",COUNTA($B$15:$B28)) | C28: =IF(OR($J28="",$J28=0),"",INDEX(BPU!$G$2:$G$117,$J28)&"") | E28: =IF($B28="","",IF($J28=0,"Hors BPU",IF(ISNUMBER($K28),ROUND($K28,2),$K28))) | H28: =IF($B28="","",IF(AND($F28="",NOT(ISNUMBER($E28))),"PU à saisir",ROUND(N($D28)*IF($F28<>"",$F28,$E28)*IF($G28="",1,IFERROR(INDEX(Majorations!$C$2:$C$3,MATCH($G28,ListeMajorations,0)),1)),2))) | J28: =IF($B28="","",IFERROR(MATCH($B28,ListePrestations,0),0)) | K28: =IF(OR($J28="",$J28=0),"",INDEX(BPU!$H$2:$H$117,$J28))
A29: =IF($B29="","",COUNTA($B$15:$B29)) | C29: =IF(OR($J29="",$J29=0),"",INDEX(BPU!$G$2:$G$117,$J29)&"") | E29: =IF($B29="","",IF($J29=0,"Hors BPU",IF(ISNUMBER($K29),ROUND($K29,2),$K29))) | H29: =IF($B29="","",IF(AND($F29="",NOT(ISNUMBER($E29))),"PU à saisir",ROUND(N($D29)*IF($F29<>"",$F29,$E29)*IF($G29="",1,IFERROR(INDEX(Majorations!$C$2:$C$3,MATCH($G29,ListeMajorations,0)),1)),2))) | J29: =IF($B29="","",IFERROR(MATCH($B29,ListePrestations,0),0)) | K29: =IF(OR($J29="",$J29=0),"",INDEX(BPU!$H$2:$H$117,$J29))
A30: =IF($B30="","",COUNTA($B$15:$B30)) | C30: =IF(OR($J30="",$J30=0),"",INDEX(BPU!$G$2:$G$117,$J30)&"") | E30: =IF($B30="","",IF($J30=0,"Hors BPU",IF(ISNUMBER($K30),ROUND($K30,2),$K30))) | H30: =IF($B30="","",IF(AND($F30="",NOT(ISNUMBER($E30))),"PU à saisir",ROUND(N($D30)*IF($F30<>"",$F30,$E30)*IF($G30="",1,IFERROR(INDEX(Majorations!$C$2:$C$3,MATCH($G30,ListeMajorations,0)),1)),2))) | J30: =IF($B30="","",IFERROR(MATCH($B30,ListePrestations,0),0)) | K30: =IF(OR($J30="",$J30=0),"",INDEX(BPU!$H$2:$H$117,$J30))
A31: =IF($B31="","",COUNTA($B$15:$B31)) | C31: =IF(OR($J31="",$J31=0),"",INDEX(BPU!$G$2:$G$117,$J31)&"") | E31: =IF($B31="","",IF($J31=0,"Hors BPU",IF(ISNUMBER($K31),ROUND($K31,2),$K31))) | H31: =IF($B31="","",IF(AND($F31="",NOT(ISNUMBER($E31))),"PU à saisir",ROUND(N($D31)*IF($F31<>"",$F31,$E31)*IF($G31="",1,IFERROR(INDEX(Majorations!$C$2:$C$3,MATCH($G31,ListeMajorations,0)),1)),2))) | J31: =IF($B31="","",IFERROR(MATCH($B31,ListePrestations,0),0)) | K31: =IF(OR($J31="",$J31=0),"",INDEX(BPU!$H$2:$H$117,$J31))
A32: =IF($B32="","",COUNTA($B$15:$B32)) | C32: =IF(OR($J32="",$J32=0),"",INDEX(BPU!$G$2:$G$117,$J32)&"") | E32: =IF($B32="","",IF($J32=0,"Hors BPU",IF(ISNUMBER($K32),ROUND($K32,2),$K32))) | H32: =IF($B32="","",IF(AND($F32="",NOT(ISNUMBER($E32))),"PU à saisir",ROUND(N($D32)*IF($F32<>"",$F32,$E32)*IF($G32="",1,IFERROR(INDEX(Majorations!$C$2:$C$3,MATCH($G32,ListeMajorations,0)),1)),2))) | J32: =IF($B32="","",IFERROR(MATCH($B32,ListePrestations,0),0)) | K32: =IF(OR($J32="",$J32=0),"",INDEX(BPU!$H$2:$H$117,$J32))
... A44: =IF($B44="","",COUNTA($B$15:$B44)) | C44: =IF(OR($J44="",$J44=0),"",INDEX(BPU!$G$2:$G$117,$J44)&"") | E44: =IF($B44="","",IF($J44=0,"Hors BPU",IF(ISNUMBER($K44),ROUND($K44,2),$K44))) | H44: =IF($B44="","",IF(AND($F44="",NOT(ISNUMBER($E44))),"PU à saisir",ROUND(N($D44)*IF($F44<>"",$F44,$E44)*IF($G44="",1,IFERROR(INDEX(Majorations!$C$2:$C$3,MATCH($G44,ListeMajorations,0)),1)),2))) | J44: =IF($B44="","",IFERROR(MATCH($B44,ListePrestations,0),0)) | K44: =IF(OR($J44="",$J44=0),"",INDEX(BPU!$H$2:$H$117,$J44))
A46: =IF(COUNTIF(H15:H44,"PU à saisir")>0,"Attention : "&COUNTIF(H15:H44,"PU à saisir")&" ligne(s) sur devis sans prix, à compléter dans la colonne « PU HT sur devis ».","") | G46: Total HT | H46: =SUM(H15:H44) -> 1241.52
A47: =IF(COUNTA(G15:G44)=0,"","Majorations BPU appliquées au montant de la ligne : MC-07 × "&FIXED(Majorations!$C$2,4)&" ; MC-08 × "&FIXED(Majorations!$C$3,4)&".") -> Majorations BPU appliquées au montant de la ligne : MC-07 × 1.4906 ; MC-08 × 1.4078. | G47: =IF(Autoliq="Oui","TVA (autoliquidation)","TVA "&TauxTVA*100&" %") -> TVA 20 % | H47: =IF(Autoliq="Oui",0,ROUND(H46*TauxTVA,2)) -> 248.3
A48: =IF(Autoliq="Oui","Autoliquidation : TVA due par le preneur (article 283-2 nonies du CGI).","") | G48: Total TTC | H48: =H46+H47 -> 1489.82
A50: CONDITIONS
A51: Prix unitaires HT issus du BPU Moselle Fibre – RHD57 (Maintenance et VDR Optique).
A52: Hors fourniture, sauf mention contraire du BPU.
A53: Conditions de paiement : à préciser.
A54: ="Devis valable jusqu'au "&IF(H5="","…",DAY(H5)&"/"&RIGHT("0"&MONTH(H5),2)&"/"&YEAR(H5))&"." -> Devis valable jusqu'au 20/11/2026.
A56: Pour l'entreprise – date, nom et signature | E56: Bon pour accord du client – date, nom, signature et cachet

Sheet BPU
A1: BPU | B1: Lot | C1: Famille | D1: Code | E1: Désignation | F1: Descriptif | G1: Unité | H1: Prix BPU € HT / u | I1: Commentaire | J1: Libellé dans le devis | K1: Source
A2: Maintenance | B2: Rémunération et conditions de paiement au titre des Prestations de raccordements des clients | C2: Raccordements | D2: RA-F1 | E2: Raccordement abonné Opera Pro (PM) | F2: Aiguillage, Tirage , Racco et mise en service quelque soit la distance et le type de raccordement ( Souterrain , Aérien,Façade, Immeuble) | G2: Forfait par opération | H2: 210 | I2: à l'acte | J2: RA-F1 · Raccordement abonné Opera Pro (PM) | K2: Maintenance BPU ST · BPU ligne 4
A3: Maintenance | B3: Rémunération et conditions de paiement au titre des Prestations de raccordements des clients | C3: Raccordements | D3: RA-F2 | E3: Raccordement abonné Opera Office (PM) | F3: Aiguillage, Tirage , Racco et mise en service quelque soit la distance et le type de raccordement ( Souterrain , Aérien,Façade, Immeuble) | G3: Forfait par opération | H3: 210 | I3: à l'acte | J3: RA-F2 · Raccordement abonné Opera Office (PM) | K3: Maintenance BPU ST · BPU ligne 5
A4: Maintenance | B4: Rémunération et conditions de paiement au titre des Prestations de raccordements des clients | C4: Raccordements | D4: RA-F3 | E4: Raccordement abonné Opera Business BLOM (PM) | F4: Aiguillage, Tirage , Racco et mise en service quelque soit la distance et le type de raccordement ( Souterrain , Aérien,Façade, Immeuble) | G4: Forfait par opération | H4: 210 | I4: à l'acte | J4: RA-F3 · Raccordement abonné Opera Business BLOM (PM) | K4: Maintenance BPU ST · BPU ligne 6
A5: Maintenance | B5: Rémunération et conditions de paiement au titre des Prestations de raccordements des clients | C5: Raccordements | D5: RA-F4 | E5: Raccordement abonné Opera Business BLOM (NRO) | F5: Aiguillage, Tirage , Racco et mise en service quelque soit la distance et le type de raccordement ( Souterrain , Aérien,Façade, Immeuble) | G5: Forfait par opération | H5: 210 | I5: à l'acte | J5: RA-F4 · Raccordement abonné Opera Business BLOM (NRO) | K5: Maintenance BPU ST · BPU ligne 7
A6: Maintenance | B6: Rémunération et conditions de paiement au titre des Prestations de raccordements des clients | C6: Raccordements | D6: RA-ON | E6: Raccordement abonné Opera Business BLOD | F6: Pré-visite : reportage photos + aiguillage de la partie privée uniquement + CRVT : 108,45€ / MES : Aiguillage de la partie publique / Tirage et Raccordement + pose des équipements (PTO + ADVA) chez le client Aiguillage Hors founiture : 351,06€ / Jusqu'à 300ml ( 0,93€/ml au dela) | G6: Forfait par opération | H6: 459.51 | I6: à l'acte | J6: RA-ON · Raccordement abonné Opera Business BLOD | K6: Maintenance BPU ST · BPU ligne 8
A7: Maintenance | B7: Rémunération et conditions de paiement au titre des Prestations de raccordements des clients | C7: Raccordements | D7: RA-ON | E7: Raccordement abonné Opera Business BLOD – ml au-delà de 300 ml | F7: Mètre linéaire au-delà des 300 ml compris dans le forfait | G7: ml | H7: 0.93 | I7: D'après le descriptif de RA-ON (« jusqu'à 300ml, 0,93€/ml au-delà ») | J7: RA-ON · Raccordement abonné Opera Business BLOD – ml au-delà de 300 ml | K7: Maintenance BPU ST · BPU ligne 8
A8: Maintenance | B8: Rémunération et conditions de paiement au titre des Prestations de raccordements des clients | C8: Raccordements | D8: RA-B1 | E8: Raccordement Service à destination des personnes âgées en situation de dépendance (BLOM) | F8: Aiguillage, Tirage , Racco et mise en service quelque soit la distance et le type de raccordement ( Souterrain , Aérien,Façade, Immeuble) | G8: Forfait par opération | H8: 210 | I8: à l'acte | J8: RA-B1 · Raccordement Service à destination des personnes âgées en situation de dépendance (BLOM) | K8: Maintenance BPU ST · BPU ligne 9
A9: Maintenance | B9: Rémunération et conditions de paiement au titre des Prestations de raccordements des clients | C9: Raccordements | D9: RA-ON | E9: Churn Opéra Pro | F9: Mise en place d'une Jarretierage au POP/NRO/PM + Pose ONT/PTO chez le client pour MES | G9: Forfait par opération | H9: 50.1875 | I9: à l'acte | J9: RA-ON · Churn Opéra Pro | K9: Maintenance BPU ST · BPU ligne 10
A10: Maintenance | B10: Rémunération et conditions de paiement au titre des Prestations de raccordements des clients | C10: Raccordements | D10: RA-B1 | E10: Churn Opéra Office | F10: Mise en place d'une Jarretierage au POP/NRO/PM + Pose ONT/PTO chez le client pour MES | G10: Forfait par opération | H10: 50.1875 | I10: à l'acte | J10: RA-B1 · Churn Opéra Office | K10: Maintenance BPU ST · BPU ligne 11
A11: Maintenance | B11: Rémunération et conditions de paiement au titre des Prestations de raccordements des clients | C11: Raccordements | D11: RA-B2 | E11: Churn Opéra Business | F11: Mise en place d'une Jarretierage au POP/NRO/PM + Pose ONT/PTO chez le client pour MES | G11: Forfait par opération | H11: 50.1875 | I11: à l'acte | J11: RA-B2 · Churn Opéra Business | K11: Maintenance BPU ST · BPU ligne 12
A12: Maintenance | B12: Rémunération et conditions de paiement au titre des Prestations de raccordements des clients | C12: Raccordements | D12: RA-RO | E12: Raccordement abonné FttO - Zone 0 (BLOD) | G12: Forfait par opération | H12: Sur devis | I12: à l'acte | J12: RA-RO · Raccordement abonné FttO - Zone 0 (BLOD) | K12: Maintenance BPU ST · BPU ligne 13
A13: Maintenance | B13: Rémunération et conditions de paiement au titre des Prestations de raccordements des clients | C13: Raccordements | D13: RA-RO | E13: Raccordement abonné FttO - Zone 1 (BLOD) | G13: Forfait par opération | H13: Sur devis | I13: à l'acte | J13: RA-RO · Raccordement abonné FttO - Zone 1 (BLOD) | K13: Maintenance BPU ST · BPU ligne 14
A14: Maintenance | B14: Rémunération et conditions de paiement au titre des Prestations de raccordements des clients | C14: Raccordements | D14: RA-RO | E14: Raccordement abonné FttO - Zone 2 (BLOD) | G14: Forfait par opération | H14: Sur devis | I14: à l'acte | J14: RA-RO · Raccordement abonné FttO - Zone 2 (BLOD) | K14: Maintenance BPU ST · BPU ligne 15
A15: Maintenance | B15: Rémunération et conditions de paiement au titre des prestations de maintenance | C15: Astreinte | D15: AS-01 | E15: Forfait mensuel pour mise à disposition d'une astreinte d'un technicien équipé | G15: Forfait global Mensuel | H15: 500 | I15: Forfait mensuel | J15: AS-01 · Forfait mensuel pour mise à disposition d'une astreinte d'un technicien équipé | K15: Maintenance BPU ST · BPU ligne 18
A16: Maintenance | B16: Rémunération et conditions de paiement au titre des prestations de maintenance | C16: Astreinte | D16: AS-02 | E16: Forfait mensuel pour mise à disposition d'un 2 ème technicien d'astreinte équipé | G16: Forfait global Mensuel | H16: 300 | I16: Forfait mensuel | J16: AS-02 · Forfait mensuel pour mise à disposition d'un 2 ème technicien d'astreinte équipé | K16: Maintenance BPU ST · BPU ligne 19
A17: Maintenance | B17: Rémunération et conditions de paiement au titre des prestations de maintenance | C17: Mini-forfait curatif | D17: MC-01 | E17: Intervention Immédiate en HO TELECOM - opérations sur equipement actif | G17: Forfait par intervention | H17: 160.34179 | I17: à l'acte | J17: MC-01 · Intervention Immédiate en HO TELECOM - opérations sur equipement actif | K17: Maintenance BPU ST · BPU ligne 22
A18: Maintenance | B18: Rémunération et conditions de paiement au titre des prestations de maintenance | C18: Mini-forfait curatif | D18: MC-02 | E18: Intervention Programmée en HO TELECOM - opérations sur equipement actif | G18: Forfait par intervention | H18: 137.72096 | I18: à l'acte | J18: MC-02 · Intervention Programmée en HO TELECOM - opérations sur equipement actif | K18: Maintenance BPU ST · BPU ligne 23
A19: Maintenance | B19: Rémunération et conditions de paiement au titre des prestations de maintenance | C19: Mini-forfait curatif | D19: MC-03 | E19: Intervention Immédiate en HO ENVIRONNEMENT - énergie, climatisation, contrôle d'accès | G19: Forfait par intervention | H19: 141.71287 | I19: à l'acte | J19: MC-03 · Intervention Immédiate en HO ENVIRONNEMENT - énergie, climatisation, contrôle d'accès | K19: Maintenance BPU ST · BPU ligne 24
A20: Maintenance | B20: Rémunération et conditions de paiement au titre des prestations de maintenance | C20: Mini-forfait curatif | D20: MC-04 | E20: Intervention Programmée en HO ENVIRONNEMENT - énergie, climatisation, contrôle d'accès | G20: Forfait par intervention | H20: 86.491422 | I20: à l'acte | J20: MC-04 · Intervention Programmée en HO ENVIRONNEMENT - énergie, climatisation, contrôle d'accès | K20: Maintenance BPU ST · BPU ligne 25
A21: Maintenance | B21: Rémunération et conditions de paiement au titre des prestations de maintenance | C21: Mini-forfait curatif | D21: MC-05 | E21: SAV et ticket à froid yc. Intervention d'un technicien en HO | G21: Forfait par intervention | H21: 50.5 | I21: à l'acte | J21: MC-05 · SAV et ticket à froid yc. Intervention d'un technicien en HO | K21: Maintenance BPU ST · BPU ligne 26
A22: Maintenance | B22: Rémunération et conditions de paiement au titre des prestations de maintenance | C22: Mini-forfait curatif | D22: MC-06 | E22: SAV et ticket à froid yc. Intervention de deux techniciens (nacelle incluse) en HO | G22: Forfait par intervention | H22: 163.62 | I22: à l'acte | J22: MC-06 · SAV et ticket à froid yc. Intervention de deux techniciens (nacelle incluse) en HO | K22: Maintenance BPU ST · BPU ligne 27
A23: Maintenance | B23: Rémunération et conditions de paiement au titre des prestations de maintenance | C23: Mini-forfait curatif | D23: MC-09 | E23: SAV GTR 10h : Intervention d'un technicien en HO | G23: Forfait par intervention | H23: 50.5 | I23: à l'acte | J23: MC-09 · SAV GTR 10h : Intervention d'un technicien en HO | K23: Maintenance BPU ST · BPU ligne 30
A24: Maintenance | B24: Rémunération et conditions de paiement au titre des prestations de maintenance | C24: Mini-forfait curatif | D24: MC-10 | E24: SAV GTR 10h : Intervention de deux techniciens (nacelle incluse) en HO | G24: Forfait par intervention | H24: 163.62 | I24: à l'acte | J24: MC-10 · SAV GTR 10h : Intervention de deux techniciens (nacelle incluse) en HO | K24: Maintenance BPU ST · BPU ligne 31
A25: Maintenance | B25: Rémunération et conditions de paiement au titre des prestations de maintenance | C25: Maintenance curative | D25: MC-T1 | E25: Heure de technicien équipé en HO (8h00 – 18h00) - Intervention Immédiate | G25: Forfait par heure | H25: 35.92625 | I25: à l'acte | J25: MC-T1 · Heure de technicien équipé en HO (8h00 – 18h00) - Intervention Immédiate | K25: Maintenance BPU ST · BPU ligne 33
A26: Maintenance | B26: Rémunération et conditions de paiement au titre des prestations de maintenance | C26: Maintenance curative | D26: MC-T2 | E26: Heure de technicien équipé en HO (8h00 – 18h00) - Intervention Programmée | G26: Forfait par heure | H26: 35.05125 | I26: à l'acte | J26: MC-T2 · Heure de technicien équipé en HO (8h00 – 18h00) - Intervention Programmée | K26: Maintenance BPU ST · BPU ligne 34
... A29: Maintenance | B29: Rémunération et conditions de paiement au titre des prestations de maintenance | C29: Maintenance curative | D29: MC-T5 | E29: Intervention de 2 techniciens équipés d'une nacelle <= 16m en HNO | G29: Forfait par heure | H29: 123.75 | I29: à l'acte | J29: MC-T5 · Intervention de 2 techniciens équipés d'une nacelle <= 16m en HNO | K29: Maintenance BPU ST · BPU ligne 37
A30: Maintenance | B30: Rémunération et conditions de paiement au titre des prestations de maintenance | C30: Maintenance curative | D30: MC-T6 | E30: Mise à disposition d'une nacelle exceptionnelle (>16m, nacelle araignée, 4x4, inversée) - un jour | G30: Par mètre (hauteur nacelle) | H30: Sur devis | I30: à l'acte | J30: MC-T6 · Mise à disposition d'une nacelle exceptionnelle (>16m, nacelle araignée, 4x4, inversée) - un… | K30: Maintenance BPU ST · BPU ligne 38
A31: Maintenance | B31: Rémunération et conditions de paiement au titre des prestations de maintenance | C31: Commandes des usagers | D31: PU-01 | E31: Installation électrique au NRO yc. fourniture et pose du tiroir optique dans la baie de transport | G31: Par commande | H31: Sur devis | I31: à l'acte | J31: PU-01 · Installation électrique au NRO yc. fourniture et pose du tiroir optique dans la baie de… | K31: Maintenance BPU ST · BPU ligne 40
A32: Maintenance | B32: Rémunération et conditions de paiement au titre des prestations de maintenance | C32: Commandes des usagers | D32: PU-02 | E32: Fourniture et pose d'un tiroir optique dans la baie de transport | G32: Par commande | H32: Sur devis | I32: à l'acte | J32: PU-02 · Fourniture et pose d'un tiroir optique dans la baie de transport | K32: Maintenance BPU ST · BPU ligne 41
A33: Maintenance | B33: Rémunération et conditions de paiement au titre des prestations de maintenance | C33: Commandes des usagers | D33: PU-03 | E33: Fourniture et pose d’une jarretière entre la baie Opérateur et la baie OCEN | G33: Par commande | H33: Sur devis | I33: à l'acte | J33: PU-03 · Fourniture et pose d’une jarretière entre la baie Opérateur et la baie OCEN | K33: Maintenance BPU ST · BPU ligne 42
A34: Maintenance | B34: Rémunération et conditions de paiement au titre des prestations de maintenance | C34: Commandes des usagers | D34: PU-04 | E34: Fourniture et pose de jarretières entre la tête de câble OC et le tiroir transport PM dans le NRO | G34: Par commande | H34: Sur devis | I34: à l'acte | J34: PU-04 · Fourniture et pose de jarretières entre la tête de câble OC et le tiroir transport PM dans le… | K34: Maintenance BPU ST · BPU ligne 43
A35: Maintenance | B35: Rémunération et conditions de paiement au titre des prestations de maintenance | C35: Commandes des usagers | D35: PU-05 | E35: Fourniture et pose au NRO d'une baie 42U yc. raccordement du PDU | G35: Par commande | H35: Sur devis | I35: à l'acte | J35: PU-05 · Fourniture et pose au NRO d'une baie 42U yc. raccordement du PDU | K35: Maintenance BPU ST · BPU ligne 44
A36: Maintenance | B36: Rémunération et conditions de paiement au titre des prestations de maintenance | C36: Commandes des usagers | D36: PU-06 | E36: Fourniture et pose au NRO d'une baie 21U yc. raccordement du PDU | G36: Par commande | H36: Sur devis | I36: à l'acte | J36: PU-06 · Fourniture et pose au NRO d'une baie 21U yc. raccordement du PDU | K36: Maintenance BPU ST · BPU ligne 45
A37: VDR Optique | B37: 1 - Infrastructures tièrces | C37: 1 - Infrastructures tièrces | D37: 1.1 | E37: Aiguillage de génie civil sous-terrain existant | F37: Ce prix rémunère au métre mesuré sur place l'aiguillage de conduite existante (réseau Orange, ou tiers) afin de vérifier la disponibilité de cette conduite en vue d'un futur passage de câble et comprend: - l'aiguillage de la conduite existante - la pose d'un filin et étiquette - la détection des points de blocage - si nécessaire, le nettoyage manuel de la chambre | G37: ml | H37: 0.4 | J37: 1.1 · Aiguillage de génie civil sous-terrain existant | K37: BPU ST VDR Optique · BPU MISSION 3 Optique ligne 5
A38: VDR Optique | B38: 1 - Infrastructures tièrces | C38: 1 - Infrastructures tièrces | D38: 1.2 | E38: Débouchage de réseaux existants à l'aide d'un camion d'hydrocurage | F38: Ce prix rémunère à l'unité le débouchage d'une conduite obstruée comprenant: - une équipe pour accès aux regards - un camion d'hydrocurage avec son personnel spécialisé et habilité - redevance pour le traitement des déchets Ce prix tient compte de la fourniture et la mise en place des signalisations chantier (déviations éventuelles, alternats manuels K10,...). | G38: U | H38: 550 | J38: 1.2 · Débouchage de réseaux existants à l'aide d'un camion d'hydrocurage | K38: BPU ST VDR Optique · BPU MISSION 3 Optique ligne 6
A39: VDR Optique | B39: 1 - Infrastructures tièrces | C39: 1 - Infrastructures tièrces | D39: 1.3 | E39: Relevé de masques de chambre FT non plafonnée et édition de la fiche FOA conformément à l'offre de référence iBLO de France Télécom, hors aiguillage | G39: U | H39: 25 | J39: 1.3 · Relevé de masques de chambre FT non plafonnée et édition de la fiche FOA conformément à… | K39: BPU ST VDR Optique · BPU MISSION 3 Optique ligne 7
A40: VDR Optique | B40: 1 - Infrastructures tièrces | C40: 1 - Infrastructures tièrces | D40: 1.4 | E40: Relevé de masques de chambre FT plafonnée et édition de la fiche FOA conformément à l'offre de référence iBLO de France Télécom, hors aiguillage | G40: U | H40: 35 | J40: 1.4 · Relevé de masques de chambre FT plafonnée et édition de la fiche FOA conformément à l'offre de… | K40: BPU ST VDR Optique · BPU MISSION 3 Optique ligne 8
A41: VDR Optique | B41: 4 - Câbles optiques, étiquetage, DOE inclus | C41: 4.1 - Pose et dépose de câbles optiques pour pose en fourreau | D41: 4.1.1 | E41: Pose de câbles à fibres optiques, G657-A2 ou G652-D , de 1 FO à 144 FO | F41: Ce prix rémunère au métre mesuré sur place la pose en fourreau de cable comprenant : - la pose de cable à fibres optiques, - le matériel nécessaire à la mise en place (soufalge à l'aire ou à l'eau, etc) - la fourniture et la mise en place des signalisations chantier (déviations éventuelles, alternats manuels K10,... | G41: ml | H41: 1 | J41: 4.1.1 · Pose de câbles à fibres optiques, G657-A2 ou G652-D , de 1 FO à 144 FO | K41: BPU ST VDR Optique · BPU MISSION 3 Optique ligne 12
A42: VDR Optique | B42: 4 - Câbles optiques, étiquetage, DOE inclus | C42: 4.1 - Pose et dépose de câbles optiques pour pose en fourreau | D42: 4.1.13 | E42: Pose de câbles à fibres optiques, G657-A2 ou G652-D , supérieur ou égal à 288FO | F42: Ce prix rémunère au métre mesuré sur place la pose en fourreau de cable comprenant : - la pose de cable à fibres optiques, - le matériel nécessaire à la mise en place (soufalge à l'aire ou à l'eau, etc) - la fourniture et la mise en place des signalisations chantier (déviations éventuelles, alternats manuels K10,... | G42: ml | H42: 1.2 | J42: 4.1.13 · Pose de câbles à fibres optiques, G657-A2 ou G652-D , supérieur ou égal à 288FO | K42: BPU ST VDR Optique · BPU MISSION 3 Optique ligne 13
A43: VDR Optique | B43: 4 - Câbles optiques, étiquetage, DOE inclus | C43: 4.1 - Pose et dépose de câbles optiques pour pose en fourreau | D43: 4.1.14 | E43: Dépose de câbles à fibres optiques | F43: Ce prix rémunère au métre mesuré sur place la pose en fourreau de cable comprenant : - la pose de cable à fibres optiques, - le matériel nécessaire à la mise en place (soufalge à l'aire ou à l'eau, etc) - la fourniture et la mise en place des signalisations chantier (déviations éventuelles, alternats manuels K10,... | G43: ml | H43: 0.45 | J43: 4.1.14 · Dépose de câbles à fibres optiques | K43: BPU ST VDR Optique · BPU MISSION 3 Optique ligne 14
A44: VDR Optique | B44: 4 - Câbles optiques, étiquetage, DOE inclus | C44: 4.1 - Pose et dépose de câbles optiques pour pose en fourreau | D44: 4.1.14 | E44: Moins-Value si pose par portage à l'air ou à l'eau dans conduite libre | F44: Ce prix rémunère au métre mesuré sur place la pose en fourreau de cable comprenant : - la pose de cable à fibres optiques, - le matériel nécessaire à la mise en place (soufalge à l'aire ou à l'eau, etc) - la fourniture et la mise en place des signalisations chantier (déviations éventuelles, alternats manuels K10,... | G44: ml | H44: -0.35 | J44: 4.1.14 · Moins-Value si pose par portage à l'air ou à l'eau dans conduite libre | K44: BPU ST VDR Optique · BPU MISSION 3 Optique ligne 15
A45: VDR Optique | B45: 4 - Câbles optiques, étiquetage, DOE inclus | C45: 4.1 - Pose et dépose de câbles optiques pour pose en fourreau | D45: 4.1.14 | E45: Moins-Value si pose par portage à l'air ou à l'aeau dans conduite occupée | F45: Ce prix rémunère au métre mesuré sur place la pose en fourreau de cable comprenant : - la pose de cable à fibres optiques, - le matériel nécessaire à la mise en place (soufalge à l'aire ou à l'eau, etc) - la fourniture et la mise en place des signalisations chantier (déviations éventuelles, alternats manuels K10,... | G45: ml | H45: -0.25 | J45: 4.1.14 · Moins-Value si pose par portage à l'air ou à l'aeau dans conduite occupée | K45: BPU ST VDR Optique · BPU MISSION 3 Optique ligne 16
A46: VDR Optique | B46: 4 - Câbles optiques, étiquetage, DOE inclus | C46: 4.2 - Pose et dépose de câbles optiques pour pose en aérien | D46: 4.2.1 | E46: Pose de câbles à fibres optiques de 1 à 12 FO | F46: Ce prix rémunère au métre mesuré sur place la pose en aérien de cable comprenant : - la pose de cable à fibres optiques, - le matériel nécessaire à la mise en place (nacelle, etc) - la fourniture et la mise en place des signalisations chantier (déviations éventuelles, alternats manuels K10,... | G46: ml | H46: 1.6 | J46: 4.2.1 · Pose de câbles à fibres optiques de 1 à 12 FO | K46: BPU ST VDR Optique · BPU MISSION 3 Optique ligne 19
A47: VDR Optique | B47: 4 - Câbles optiques, étiquetage, DOE inclus | C47: 4.2 - Pose et dépose de câbles optiques pour pose en aérien | D47: 4.2.5 | E47: Pose de câbles à fibres optiques de 24 FO à 144 FO | F47: Ce prix rémunère au métre mesuré sur place la pose en aérien de cable comprenant : - la pose de cable à fibres optiques, - le matériel nécessaire à la mise en place (nacelle, etc) - la fourniture et la mise en place des signalisations chantier (déviations éventuelles, alternats manuels K10,... | G47: ml | H47: 1.8 | J47: 4.2.5 · Pose de câbles à fibres optiques de 24 FO à 144 FO | K47: BPU ST VDR Optique · BPU MISSION 3 Optique ligne 20
A48: VDR Optique | B48: 4 - Câbles optiques, étiquetage, DOE inclus | C48: 4.2 - Pose et dépose de câbles optiques pour pose en aérien | D48: 4.2.11 | E48: Plus-value pour pose de câbles optiques sur façade | F48: Ce prix rémunère au métre mesuré sur place la pose en aérien de cable comprenant : - la pose de cable à fibres optiques, - le matériel nécessaire à la mise en place (nacelle, etc) - la fourniture et la mise en place des signalisations chantier (déviations éventuelles, alternats manuels K10,... | G48: ml | H48: 1.3 | J48: 4.2.11 · Plus-value pour pose de câbles optiques sur façade | K48: BPU ST VDR Optique · BPU MISSION 3 Optique ligne 21
A49: VDR Optique | B49: 4 - Câbles optiques, étiquetage, DOE inclus | C49: 4.2 - Pose et dépose de câbles optiques pour pose en aérien | D49: 4.2.12 | E49: Dépose de câbles à fibres optiques | F49: Ce prix rémunère au métre mesuré sur place la pose en aérien de cable comprenant : - la pose de cable à fibres optiques, - le matériel nécessaire à la mise en place (nacelle, etc) - la fourniture et la mise en place des signalisations chantier (déviations éventuelles, alternats manuels K10,... | G49: ml | H49: 0.45 | J49: 4.2.12 · Dépose de câbles à fibres optiques | K49: BPU ST VDR Optique · BPU MISSION 3 Optique ligne 22
A50: VDR Optique | B50: 4 - Câbles optiques, étiquetage, DOE inclus | C50: 4.2 - Pose et dépose de câbles optiques pour pose en aérien | D50: 2.9.16 | E50: Armement appui commun existant | F50: Ce prix rémunère au poteau la fourniture et la mise en place de l'armement sur appui existant et comprend la fourniture et pose de l'armement suivant configuration de l'appui (pinces d'ancrage pour fixation du cable sur l'appui existant, console, feuillard, réhausse, traverse, dispositif de suspension du cable ) | G50: u | H50: 35 | J50: 2.9.16 · Armement appui commun existant | K50: BPU ST VDR Optique · BPU MISSION 3 Optique ligne 23
A51: VDR Optique | B51: 4 - Câbles optiques, étiquetage, DOE inclus | C51: 4.3 - Pose et dépose de boîtiers de protection d'épissures (BPE) souterrains | D51: 4.3.1 | E51: Pose boitier pour protection d'épissure, capacité jusqu'à 12 épissures | F51: Ce prix rémunère à l'unité la pose d'un Boitier de Protection d'Epissure comprenant : - la pose du BPE et sa fixation en chambre - les raccordements des fibres - la fourniture et la mise en place des signalisations chantier (déviations éventuelles, alternats manuels K10,... | G51: u | H51: 100 | J51: 4.3.1 · Pose boitier pour protection d'épissure, capacité jusqu'à 12 épissures | K51: BPU ST VDR Optique · BPU MISSION 3 Optique ligne 26
A52: VDR Optique | B52: 4 - Câbles optiques, étiquetage, DOE inclus | C52: 4.3 - Pose et dépose de boîtiers de protection d'épissures (BPE) souterrains | D52: 4.3.2 | E52: Pose boitier pour protection d'épissure, capacité jusqu'à 24 épissures | F52: Ce prix rémunère à l'unité la pose d'un Boitier de Protection d'Epissure comprenant : - la pose du BPE et sa fixation en chambre - les raccordements des fibres - la fourniture et la mise en place des signalisations chantier (déviations éventuelles, alternats manuels K10,... | G52: u | H52: 130 | J52: 4.3.2 · Pose boitier pour protection d'épissure, capacité jusqu'à 24 épissures | K52: BPU ST VDR Optique · BPU MISSION 3 Optique ligne 27
... A72: VDR Optique | B72: 4 - Câbles optiques, étiquetage, DOE inclus | C72: 4.5 - Dispositif de Raccordement optique | D72: 4.5.2 | E72: Pose de PBO en chambre | F72: Ce prix rémunère à l'unité : - la pose en sécurité d'un PBO, d'un boitier terminal ou d'un bandeau - le raccordement des fibres aux points techniques - la fourniture et la mise en place des signalisations chantier (déviations éventuelles, alternats manuels K10,...) | G72: U | H72: 60 | J72: 4.5.2 · Pose de PBO en chambre | K72: BPU ST VDR Optique · BPU MISSION 3 Optique ligne 51
A73: VDR Optique | B73: 4 - Câbles optiques, étiquetage, DOE inclus | C73: 4.5 - Dispositif de Raccordement optique | D73: 4.5.6 | E73: Pose de tiroir optique 19" 288 FO équipé des cassettes, des traversées et des pigtails fibre (connectique SC/APC), y compris de fixation et étiquetage. | F73: Ce prix rémunère à l'unité : - la pose en sécurité d'un PBO, d'un boitier terminal ou d'un bandeau - le raccordement des fibres aux points techniques - la fourniture et la mise en place des signalisations chantier (déviations éventuelles, alternats manuels K10,...) | G73: U | H73: 90 | I73: Hors Raccordement - Utilisation en plus de l'ARTICLE 4.8 - Raccordement fibre optique | J73: 4.5.6 · Pose de tiroir optique 19" 288 FO équipé des cassettes, des traversées et des pigtails fibre… | K73: BPU ST VDR Optique · BPU MISSION 3 Optique ligne 52
A74: VDR Optique | B74: 4 - Câbles optiques, étiquetage, DOE inclus | C74: 4.5 - Dispositif de Raccordement optique | D74: 4.5.7 | E74: Pose de tiroir optique 19" 144 FO équipé des cassettes, des traversées et des pigtails fibre (connectique SC/APC), y compris de fixation et étiquetage. | F74: Ce prix rémunère à l'unité : - la pose en sécurité d'un PBO, d'un boitier terminal ou d'un bandeau - le raccordement des fibres aux points techniques - la fourniture et la mise en place des signalisations chantier (déviations éventuelles, alternats manuels K10,...) | G74: U | H74: 90 | I74: Hors Raccordement - Utilisation en plus de l'ARTICLE 4.8 - Raccordement fibre optique | J74: 4.5.7 · Pose de tiroir optique 19" 144 FO équipé des cassettes, des traversées et des pigtails fibre… | K74: BPU ST VDR Optique · BPU MISSION 3 Optique ligne 53
A75: VDR Optique | B75: 4 - Câbles optiques, étiquetage, DOE inclus | C75: 4.5 - Dispositif de Raccordement optique | D75: 4.5.8 | E75: Pose de tiroir optique 19" 96 FO équipé des cassettes, des traversées et des pigtails fibre (connectique SC/APC), y compris de fixation et étiquetage. | F75: Ce prix rémunère à l'unité : - la pose en sécurité d'un PBO, d'un boitier terminal ou d'un bandeau - le raccordement des fibres aux points techniques - la fourniture et la mise en place des signalisations chantier (déviations éventuelles, alternats manuels K10,...) | G75: U | H75: 90 | I75: Hors Raccordement - Utilisation en plus de l'ARTICLE 4.8 - Raccordement fibre optique | J75: 4.5.8 · Pose de tiroir optique 19" 96 FO équipé des cassettes, des traversées et des pigtails fibre… | K75: BPU ST VDR Optique · BPU MISSION 3 Optique ligne 54
A76: VDR Optique | B76: 4 - Câbles optiques, étiquetage, DOE inclus | C76: 4.5 - Dispositif de Raccordement optique | D76: 4.5.9 | E76: Pose de tiroir optique 19" 72 FO équipé des cassettes, des traversées et des pigtails fibre (connectique SC/APC), y compris de fixation et étiquetage. | F76: Ce prix rémunère à l'unité : - la pose en sécurité d'un PBO, d'un boitier terminal ou d'un bandeau - le raccordement des fibres aux points techniques - la fourniture et la mise en place des signalisations chantier (déviations éventuelles, alternats manuels K10,...) | G76: U | H76: 90 | I76: Hors Raccordement - Utilisation en plus de l'ARTICLE 4.8 - Raccordement fibre optique | J76: 4.5.9 · Pose de tiroir optique 19" 72 FO équipé des cassettes, des traversées et des pigtails fibre… | K76: BPU ST VDR Optique · BPU MISSION 3 Optique ligne 55
A77: VDR Optique | B77: 4 - Câbles optiques, étiquetage, DOE inclus | C77: 4.5 - Dispositif de Raccordement optique | D77: 4.5.10 | E77: Pose de Tiroir optique 19" 48 FO équipé des cassettes, des traversées et des pigtails fibre (connectique SC/APC), y compris de fixation et étiquetage. | F77: Ce prix rémunère à l'unité : - la pose en sécurité d'un PBO, d'un boitier terminal ou d'un bandeau - le raccordement des fibres aux points techniques - la fourniture et la mise en place des signalisations chantier (déviations éventuelles, alternats manuels K10,...) | G77: U | H77: 90 | I77: Hors Raccordement - Utilisation en plus de l'ARTICLE 4.8 - Raccordement fibre optique | J77: 4.5.10 · Pose de Tiroir optique 19" 48 FO équipé des cassettes, des traversées et des pigtails fibre… | K77: BPU ST VDR Optique · BPU MISSION 3 Optique ligne 56
A78: VDR Optique | B78: 4 - Câbles optiques, étiquetage, DOE inclus | C78: 4.5 - Dispositif de Raccordement optique | D78: 4.5.11 | E78: Pose de tiroir optique 19" 48 FO pour le lovage | F78: Ce prix rémunère à l'unité : - la pose en sécurité d'un PBO, d'un boitier terminal ou d'un bandeau - le raccordement des fibres aux points techniques - la fourniture et la mise en place des signalisations chantier (déviations éventuelles, alternats manuels K10,...) | G78: U | H78: 30 | I78: Hors Raccordement - Utilisation en plus de l'ARTICLE 4.8 - Raccordement fibre optique | J78: 4.5.11 · Pose de tiroir optique 19" 48 FO pour le lovage | K78: BPU ST VDR Optique · BPU MISSION 3 Optique ligne 57
A79: VDR Optique | B79: 4 - Câbles optiques, étiquetage, DOE inclus | C79: 4.5 - Dispositif de Raccordement optique | D79: 4.5.12 | E79: Pose de tiroir optique 19" 36 FO équipé des cassettes, des traversées et des pigtails fibre (connectique ST/APC), y compris de fixation et étiquetage. | F79: Ce prix rémunère à l'unité : - la pose en sécurité d'un PBO, d'un boitier terminal ou d'un bandeau - le raccordement des fibres aux points techniques - la fourniture et la mise en place des signalisations chantier (déviations éventuelles, alternats manuels K10,...) | G79: U | H79: 90 | I79: Hors Raccordement - Utilisation en plus de l'ARTICLE 4.8 - Raccordement fibre optique | J79: 4.5.12 · Pose de tiroir optique 19" 36 FO équipé des cassettes, des traversées et des pigtails fibre… | K79: BPU ST VDR Optique · BPU MISSION 3 Optique ligne 58
A80: VDR Optique | B80: 4 - Câbles optiques, étiquetage, DOE inclus | C80: 4.5 - Dispositif de Raccordement optique | D80: 4.5.13 | E80: Pose de Tiroir optique 19" 24 FO équipé des cassettes, des traversées et des pigtails fibre (connectique SC/APC), y compris de fixation et étiquetage. | F80: Ce prix rémunère à l'unité : - la pose en sécurité d'un PBO, d'un boitier terminal ou d'un bandeau - le raccordement des fibres aux points techniques - la fourniture et la mise en place des signalisations chantier (déviations éventuelles, alternats manuels K10,...) | G80: U | H80: 90 | I80: Hors Raccordement - Utilisation en plus de l'ARTICLE 4.8 - Raccordement fibre optique | J80: 4.5.13 · Pose de Tiroir optique 19" 24 FO équipé des cassettes, des traversées et des pigtails fibre… | K80: BPU ST VDR Optique · BPU MISSION 3 Optique ligne 59
A81: VDR Optique | B81: 4 - Câbles optiques, étiquetage, DOE inclus | C81: 4.5 - Dispositif de Raccordement optique | D81: 4.5.14 | E81: Pose de tiroir optique 19" 12 FO équipé des cassettes, des traversées et des pigtails fibre (connectique ST/APC), y compris de fixation et étiquetage. | F81: Ce prix rémunère à l'unité : - la pose en sécurité d'un PBO, d'un boitier terminal ou d'un bandeau - le raccordement des fibres aux points techniques - la fourniture et la mise en place des signalisations chantier (déviations éventuelles, alternats manuels K10,...) | G81: U | H81: 90 | I81: Hors Raccordement - Utilisation en plus de l'ARTICLE 4.8 - Raccordement fibre optique | J81: 4.5.14 · Pose de tiroir optique 19" 12 FO équipé des cassettes, des traversées et des pigtails fibre… | K81: BPU ST VDR Optique · BPU MISSION 3 Optique ligne 60
A82: VDR Optique | B82: 4 - Câbles optiques, étiquetage, DOE inclus | C82: 4.5 - Dispositif de Raccordement optique | D82: 4.5.15 | E82: Réintervention sur PBO poteau/façade | F82: Ce prix rémunère à l'unité : - la pose en sécurité d'un PBO, d'un boitier terminal ou d'un bandeau - le raccordement des fibres aux points techniques - la fourniture et la mise en place des signalisations chantier (déviations éventuelles, alternats manuels K10,...) | G82: U | H82: 80 | J82: 4.5.15 · Réintervention sur PBO poteau/façade | K82: BPU ST VDR Optique · BPU MISSION 3 Optique ligne 61
A83: VDR Optique | B83: 4 - Câbles optiques, étiquetage, DOE inclus | C83: 4.5 - Dispositif de Raccordement optique | D83: 4.5.16 | E83: Dépose de PBO poteau/façade | F83: Ce prix rémunère à l'unité : - la pose en sécurité d'un PBO, d'un boitier terminal ou d'un bandeau - le raccordement des fibres aux points techniques - la fourniture et la mise en place des signalisations chantier (déviations éventuelles, alternats manuels K10,...) | G83: U | H83: 40 | J83: 4.5.16 · Dépose de PBO poteau/façade | K83: BPU ST VDR Optique · BPU MISSION 3 Optique ligne 62
A84: VDR Optique | B84: 4 - Câbles optiques, étiquetage, DOE inclus | C84: 4.5 - Dispositif de Raccordement optique | D84: 4.5.17 | E84: Réintervention sur PBO en chambre | F84: Ce prix rémunère à l'unité : - la pose en sécurité d'un PBO, d'un boitier terminal ou d'un bandeau - le raccordement des fibres aux points techniques - la fourniture et la mise en place des signalisations chantier (déviations éventuelles, alternats manuels K10,...) | G84: U | H84: 60 | J84: 4.5.17 · Réintervention sur PBO en chambre | K84: BPU ST VDR Optique · BPU MISSION 3 Optique ligne 63
A85: VDR Optique | B85: 4 - Câbles optiques, étiquetage, DOE inclus | C85: 4.5 - Dispositif de Raccordement optique | D85: 4.5.18 | E85: Dépose de PBO en chambre | F85: Ce prix rémunère à l'unité : - la pose en sécurité d'un PBO, d'un boitier terminal ou d'un bandeau - le raccordement des fibres aux points techniques - la fourniture et la mise en place des signalisations chantier (déviations éventuelles, alternats manuels K10,...) | G85: U | H85: 50 | J85: 4.5.18 · Dépose de PBO en chambre | K85: BPU ST VDR Optique · BPU MISSION 3 Optique ligne 64
A86: VDR Optique | B86: 4 - Câbles optiques, étiquetage, DOE inclus | C86: 4.6 - Colonnes montantes | D86: 4.6.1 | E86: installation du réseau de distribution vertical (immeuble de 4 à 12 locaux), y compris la colonne montante, adduction, percements, la pose des PBO, la pose du câble | F86: Ce prix rémunère à l'unité la pose d'un Point de Branchement Optique comprenant : - la pose du BPO en immeuble (en colonne montante ou en pied d'immeuble) - l'adduction de l'immeuble - les percements de colonne montante - le cheminement à l'intérieur de l immeuble | G86: Forfait | H86: 300 | J86: 4.6.1 · installation du réseau de distribution vertical (immeuble de 4 à 12 locaux), y compris la… | K86: BPU ST VDR Optique · BPU MISSION 3 Optique ligne 66
A87: VDR Optique | B87: 4 - Câbles optiques, étiquetage, DOE inclus | C87: 4.6 - Colonnes montantes | D87: 4.6.2 | E87: installation du réseau vertical (par tranche de 12 locaux à partir de 13 locaux) y compris la colonne montante, adduction, percements, la fourniture et pose des PBO, la fourniture et pose du câble | F87: Ce prix rémunère la pose d'un Point de Branchement Optique comprenant : - la pose du/des BPO en immeuble - les percements de colone montante - le cheminement à l'intérieur de l immeuble Cet item est utilisé en supplément de l'item 4,6,1 | G87: Forfait | H87: 250 | J87: 4.6.2 · installation du réseau vertical (par tranche de 12 locaux à partir de 13 locaux) y compris la… | K87: BPU ST VDR Optique · BPU MISSION 3 Optique ligne 67
A88: VDR Optique | B88: 4 - Câbles optiques, étiquetage, DOE inclus | C88: 4.6 - Colonnes montantes | D88: 4.6.3 | E88: Réintervention sur PBO immeuble | G88: u | H88: 80 | J88: 4.6.3 · Réintervention sur PBO immeuble | K88: BPU ST VDR Optique · BPU MISSION 3 Optique ligne 68
A89: VDR Optique | B89: 4 - Câbles optiques, étiquetage, DOE inclus | C89: 4.6 - Colonnes montantes | D89: 4.6.4 | E89: Dépose de PBO immeuble | G89: u | H89: 50 | J89: 4.6.4 · Dépose de PBO immeuble | K89: BPU ST VDR Optique · BPU MISSION 3 Optique ligne 69
A90: VDR Optique | B90: 4 - Câbles optiques, étiquetage, DOE inclus | C90: 4.7 - Mesures réflectométries | D90: 4.7.1 | E90: Mesures réflectométriques de fibre otpique dans les deux sens aux longueurs d’onde 1310 nm et 1550 nm | G90: u (à la fibre) | H90: 5 | I90: à la fibre | J90: 4.7.1 · Mesures réflectométriques de fibre otpique dans les deux sens aux longueurs d’onde 1310 nm et… | K90: BPU ST VDR Optique · BPU MISSION 3 Optique ligne 71
A91: VDR Optique | B91: 4 - Câbles optiques, étiquetage, DOE inclus | C91: 4.7 - Mesures réflectométries | D91: 4.7.2 | E91: Mesures réflectométriques entre le PM et le PBO dans un sens aux longueurs d’onde 1550 nm sur une fibre connectorisée sur tiroir et test de continuité et de concordance fibre à fibre | G91: u (à la fibre) | H91: 3.5 | I91: à la fibre | J91: 4.7.2 · Mesures réflectométriques entre le PM et le PBO dans un sens aux longueurs d’onde 1550 nm sur… | K91: BPU ST VDR Optique · BPU MISSION 3 Optique ligne 72
A92: VDR Optique | B92: 4 - Câbles optiques, étiquetage, DOE inclus | C92: 4.8 - Raccordement fibre optique | D92: 4.8.1 | E92: Raccordement par fibre sur câble optique inférieur ou égal à 24FO | G92: u (à la fibre) | H92: 4.5 | I92: à la fibre | J92: 4.8.1 · Raccordement par fibre sur câble optique inférieur ou égal à 24FO | K92: BPU ST VDR Optique · BPU MISSION 3 Optique ligne 74
A93: VDR Optique | B93: 4 - Câbles optiques, étiquetage, DOE inclus | C93: 4.8 - Raccordement fibre optique | D93: 4.8.2 | E93: Raccordement par fibre sur câble optique de 25 à 72FO | G93: u (à la fibre) | H93: 4 | I93: à la fibre | J93: 4.8.2 · Raccordement par fibre sur câble optique de 25 à 72FO | K93: BPU ST VDR Optique · BPU MISSION 3 Optique ligne 75
A94: VDR Optique | B94: 4 - Câbles optiques, étiquetage, DOE inclus | C94: 4.8 - Raccordement fibre optique | D94: 4.8.3 | E94: Raccordement par fibre sur câble optique de 73 à 144 FO | G94: u (à la fibre) | H94: 3.5 | I94: à la fibre | J94: 4.8.3 · Raccordement par fibre sur câble optique de 73 à 144 FO | K94: BPU ST VDR Optique · BPU MISSION 3 Optique ligne 76
A95: VDR Optique | B95: 4 - Câbles optiques, étiquetage, DOE inclus | C95: 4.8 - Raccordement fibre optique | D95: 4.8.4 | E95: Raccordement par fibre sur câble optique de 145 à 288FO | G95: u (à la fibre) | H95: 3.3 | I95: à la fibre | J95: 4.8.4 · Raccordement par fibre sur câble optique de 145 à 288FO | K95: BPU ST VDR Optique · BPU MISSION 3 Optique ligne 77
A96: VDR Optique | B96: 4 - Câbles optiques, étiquetage, DOE inclus | C96: 4.9 - Pose et dépose de jarretière/cordon optique | D96: 4.9.1 | E96: Pose de jarretière/cordon optique | G96: u | H96: 3 | J96: 4.9.1 · Pose de jarretière/cordon optique | K96: BPU ST VDR Optique · BPU MISSION 3 Optique ligne 79
A97: VDR Optique | B97: 4 - Câbles optiques, étiquetage, DOE inclus | C97: 4.9 - Pose et dépose de jarretière/cordon optique | D97: 4.9.2 | E97: Dépose de jarretière/cordon optique | G97: u | H97: 3 | J97: 4.9.2 · Dépose de jarretière/cordon optique | K97: BPU ST VDR Optique · BPU MISSION 3 Optique ligne 80
A98: VDR Optique | B98: 5 - Câble réseau | C98: 5 - Câble réseau | D98: 5.1 | E98: Pose d'un câble cuivre cat 6A-500Mhz extérieur avec protection anti-rongeur type ELBAC 219545-00 ou équivalent , Il devra être livré, posé, raccordé et recetté. | G98: ml | H98: 2.4 | J98: 5.1 · Pose d'un câble cuivre cat 6A-500Mhz extérieur avec protection anti-rongeur type ELBAC… | K98: BPU ST VDR Optique · BPU MISSION 3 Optique ligne 82
A99: VDR Optique | B99: 5 - Câble réseau | C99: 5 - Câble réseau | D99: 5.2 | E99: Pose d'un câble d'installation étanche extérieur/intérieur CAT6A F/UTP monobrin Cuivre 500 Mhz type BELDEN OSP6AE ou équivalent, Il devra être livré, posé, raccordé et recetté. | G99: ml | H99: 2.4 | J99: 5.2 · Pose d'un câble d'installation étanche extérieur/intérieur CAT6A F/UTP monobrin Cuivre 500 Mhz… | K99: BPU ST VDR Optique · BPU MISSION 3 Optique ligne 83
A100: VDR Optique | B100: 5 - Câble réseau | C100: 5 - Câble réseau | D100: 5.3 | E100: Pose d'un câble cuivre cat 6A-500Mhz extérieur aérien autoporté type ELBAC 259545-00 ou équivalent , Il devra être livré, posé, raccordé et recetté. Son prix au linéaire inclu aussi les accessoires d'attache et de fixations en aérien sur poteau. | G100: ml | H100: 3 | J100: 5.3 · Pose d'un câble cuivre cat 6A-500Mhz extérieur aérien autoporté type ELBAC 259545-00 ou… | K100: BPU ST VDR Optique · BPU MISSION 3 Optique ligne 84
A101: VDR Optique | B101: 6 - Câble fibre optique hybride | C101: 6 - Câble fibre optique hybride | D101: 6.1 | E101: Pose d'un câble de raccordement hybride ( communication + alimentation électrique) extérieur type ACOME B0062A ou équivalent. Il devra disposer sous la même enveloppe en polyéthylène d'un câble optique UNC composé de 4 fibres optiques OS2 et d'un câble d'energie H07RN-F composé de 3 conducteurs cuivre de diammetre 2,5mm. | G101: ml | H101: 2.4 | J101: 6.1 · Pose d'un câble de raccordement hybride ( communication + alimentation électrique) extérieur… | K101: BPU ST VDR Optique · BPU MISSION 3 Optique ligne 86
A102: VDR Optique | B102: 6 - Câble fibre optique hybride | C102: 6 - Câble fibre optique hybride | D102: 6.2 | E102: Pose d'un câble de raccordement extérieur à fibre optique hybride composé de :2 conducteurs cuivre AWG 12 et de 2 fibres type OS2 préconnectorisé type BELDEN HDSB0020212RC ou équivalent. | G102: ml | H102: 2.4 | J102: 6.2 · Pose d'un câble de raccordement extérieur à fibre optique hybride composé de :2 conducteurs… | K102: BPU ST VDR Optique · BPU MISSION 3 Optique ligne 87
A103: VDR Optique | B103: 7 - Réalisation de raccordement terminal optique | C103: 7 - Réalisation de raccordement terminal optique | D103: 7.1.1 | E103: Réalisation d'un raccordement terminal sur un PBO intérieur <100ml – Prix pour ≥ 4 raccordements planifiés dans une même journée | F103: Ce prix rémunère par ligne FTTH la réalisation d'un raccordement terminal sur un PBO comprenant : - la pose d'une prise terminale (PTO) (fourniture et la pose du cable fibre optique zero halogène entre le PBO et la PTO) - la prise de RDV et la plannification de l'intervention - la réutilisation du cheminement existant - le raccordement au niveau du PBO intérieur - Vérification par test au crayon optique - Fourniture d'un compte rendu d'intervention | G103: Forfait | H103: 65 | J103: 7.1.1 · Réalisation d'un raccordement terminal sur un PBO intérieur <100ml – Prix pour ≥ 4… | K103: BPU ST VDR Optique · BPU MISSION 3 Optique ligne 89
A104: VDR Optique | B104: 7 - Réalisation de raccordement terminal optique | C104: 7 - Réalisation de raccordement terminal optique | D104: 7.1.2 | E104: Réalisation d'un raccordement terminal sur un PBO intérieur <100ml – Prix pour <4 raccordements planifiés dans une même journée | F104: Ce prix rémunère par ligne FTTH la réalisation d'un raccordement terminal sur un PBO comprenant : - la pose d'une prise terminale (PTO) (fourniture et la pose du cable fibre optique zero halogène entre le PBO et la PTO) - la prise de RDV et la plannification de l'intervention - la réutilisation du cheminement existant - le raccordement au niveau du PBO intérieur - Vérification par test au crayon optique - Fourniture d'un compte rendu d'intervention | G104: Forfait | H104: 80 | J104: 7.1.2 · Réalisation d'un raccordement terminal sur un PBO intérieur <100ml – Prix pour <4… | K104: BPU ST VDR Optique · BPU MISSION 3 Optique ligne 90
A105: VDR Optique | B105: 7 - Réalisation de raccordement terminal optique | C105: 7 - Réalisation de raccordement terminal optique | D105: 7.2.1 | E105: Réalisation d'un raccordement terminal sur un PBO extérieur en chambre <100ml – Prix pour ≥ 4 raccordements planifiés dans une même journée | F105: Ce prix rémunère par ligne FTTH la réalisation d'un raccordement terminal sur un PBO comprenant : - la pose d'une prise terminale (PTO) (fourniture et la pose du cable fibre optique zero halogène entre le PBO et la PTO) - la prise de RDV et la plannification de l'intervention - la réutilisation du cheminement existant - le raccordement au niveau du PBO intérieur - Vérification par test au crayon optique - Fourniture d'un compte rendu d'intervention | G105: Forfait | H105: 120 | J105: 7.2.1 · Réalisation d'un raccordement terminal sur un PBO extérieur en chambre <100ml – Prix pour ≥ 4… | K105: BPU ST VDR Optique · BPU MISSION 3 Optique ligne 91
A106: VDR Optique | B106: 7 - Réalisation de raccordement terminal optique | C106: 7 - Réalisation de raccordement terminal optique | D106: 7.2.2 | E106: Réalisation d'un raccordement terminal sur un PBO extérieur en chambre <100ml – Prix pour <4 raccordements planifiés dans une même journée | F106: Ce prix rémunère par ligne FTTH la réalisation d'un raccordement terminal sur un PBO comprenant : - la pose d'une prise terminale (PTO) (fourniture et la pose du cable fibre optique zero halogène entre le PBO et la PTO) - la prise de RDV et la plannification de l'intervention - la réutilisation du cheminement existant - le raccordement au niveau du PBO intérieur - Vérification par test au crayon optique - Fourniture d'un compte rendu d'intervention | G106: Forfait | H106: 140 | J106: 7.2.2 · Réalisation d'un raccordement terminal sur un PBO extérieur en chambre <100ml – Prix pour <4… | K106: BPU ST VDR Optique · BPU MISSION 3 Optique ligne 92
A107: VDR Optique | B107: 7 - Réalisation de raccordement terminal optique | C107: 7 - Réalisation de raccordement terminal optique | D107: 7.3.1 | E107: Réalisation d'un raccordement terminal sur un PBO extérieur aérien <100ml – Prix pour ≥ 4 raccordements planifiés dans une même journée | F107: Ce prix rémunère par ligne FTTH la réalisation d'un raccordement terminal sur un PBO comprenant : - la pose d'une prise terminale (PTO) (fourniture et la pose du cable fibre optique zero halogène entre le PBO et la PTO) - la prise de RDV et la plannification de l'intervention - la réutilisation du cheminement existant - le raccordement au niveau du PBO intérieur - Vérification par test au crayon optique - Fourniture d'un compte rendu d'intervention | G107: Forfait | H107: 150 | J107: 7.3.1 · Réalisation d'un raccordement terminal sur un PBO extérieur aérien <100ml – Prix pour ≥ 4… | K107: BPU ST VDR Optique · BPU MISSION 3 Optique ligne 93
A108: VDR Optique | B108: 7 - Réalisation de raccordement terminal optique | C108: 7 - Réalisation de raccordement terminal optique | D108: 7.3.2 | E108: Réalisation d'un raccordement terminal sur un PBO extérieur aérien <100ml – Prix pour <4 raccordements planifiés dans une même journée | F108: Ce prix rémunère par ligne FTTH la réalisation d'un raccordement terminal sur un PBO comprenant : - la pose d'une prise terminale (PTO) (fourniture et la pose du cable fibre optique zero halogène entre le PBO et la PTO) - la prise de RDV et la plannification de l'intervention - la réutilisation du cheminement existant - le raccordement au niveau du PBO intérieur - Vérification par test au crayon optique - Fourniture d'un compte rendu d'intervention | G108: Forfait | H108: 170 | J108: 7.3.2 · Réalisation d'un raccordement terminal sur un PBO extérieur aérien <100ml – Prix pour <4… | K108: BPU ST VDR Optique · BPU MISSION 3 Optique ligne 94
A109: VDR Optique | B109: 7 - Réalisation de raccordement terminal optique | C109: 7 - Réalisation de raccordement terminal optique | D109: 7.4.1 | E109: Réalisation d'un raccordement terminal sur un PBO extérieur en façade <100ml – Prix pour ≥ 4 raccordements planifiés dans une même journée | F109: Ce prix rémunère par ligne FTTH la réalisation d'un raccordement terminal sur un PBO comprenant : - la pose d'une prise terminale (PTO) (fourniture et la pose du cable fibre optique zero halogène entre le PBO et la PTO) - la prise de RDV et la plannification de l'intervention - la réutilisation du cheminement existant - le raccordement au niveau du PBO intérieur - Vérification par test au crayon optique - Fourniture d'un compte rendu d'intervention | G109: Forfait | H109: 150 | J109: 7.4.1 · Réalisation d'un raccordement terminal sur un PBO extérieur en façade <100ml – Prix pour ≥ 4… | K109: BPU ST VDR Optique · BPU MISSION 3 Optique ligne 95
A110: VDR Optique | B110: 7 - Réalisation de raccordement terminal optique | C110: 7 - Réalisation de raccordement terminal optique | D110: 7.4.2 | E110: Réalisation d'un raccordement terminal sur un PBO extérieur en façade <100ml – Prix pour <4 raccordements planifiés dans une même journée | F110: Ce prix rémunère par ligne FTTH la réalisation d'un raccordement terminal sur un PBO comprenant : - la pose d'une prise terminale (PTO) (fourniture et la pose du cable fibre optique zero halogène entre le PBO et la PTO) - la prise de RDV et la plannification de l'intervention - la réutilisation du cheminement existant - le raccordement au niveau du PBO intérieur - Vérification par test au crayon optique - Fourniture d'un compte rendu d'intervention | G110: Forfait | H110: 170 | J110: 7.4.2 · Réalisation d'un raccordement terminal sur un PBO extérieur en façade <100ml – Prix pour <4… | K110: BPU ST VDR Optique · BPU MISSION 3 Optique ligne 96
A111: VDR Optique | B111: 8 - Dispositif électrique | C111: 8 - Dispositif électrique | D111: 8.1.1 | E111: Pose et raccordement d'un câble électrique U-1000 R2V 3G1.5 mm² | G111: ml | H111: 1.8 | J111: 8.1.1 · Pose et raccordement d'un câble électrique U-1000 R2V 3G1.5 mm² | K111: BPU ST VDR Optique · BPU MISSION 3 Optique ligne 98
A112: VDR Optique | B112: 8 - Dispositif électrique | C112: 8 - Dispositif électrique | D112: 8.1.2 | E112: Pose et raccordement d'un câble électrique U-1000 R2V 3G2.5 mm² | G112: ml | H112: 1.8 | J112: 8.1.2 · Pose et raccordement d'un câble électrique U-1000 R2V 3G2.5 mm² | K112: BPU ST VDR Optique · BPU MISSION 3 Optique ligne 99
A113: VDR Optique | B113: 8 - Dispositif électrique | C113: 8 - Dispositif électrique | D113: 8.1.3 | E113: Pose et raccordement d'un câble électrique U-1000 R2V 3G6 mm² | G113: ml | H113: 1.8 | J113: 8.1.3 · Pose et raccordement d'un câble électrique U-1000 R2V 3G6 mm² | K113: BPU ST VDR Optique · BPU MISSION 3 Optique ligne 100
A114: VDR Optique | B114: 8 - Dispositif électrique | C114: 8 - Dispositif électrique | D114: 8.1.4 | E114: Pose et raccordement d'un disjoncteur différentiel bipolaire 230V 30 mA | G114: U | H114: 30 | J114: 8.1.4 · Pose et raccordement d'un disjoncteur différentiel bipolaire 230V 30 mA | K114: BPU ST VDR Optique · BPU MISSION 3 Optique ligne 101
A115: VDR Optique | B115: 8 - Dispositif électrique | C115: 8 - Dispositif électrique | D115: 8.2 | E115: Pose et raccordement d'un para-foudre modulaire 230V | G115: U | H115: 30 | J115: 8.2 · Pose et raccordement d'un para-foudre modulaire 230V | K115: BPU ST VDR Optique · BPU MISSION 3 Optique ligne 102
A116: VDR Optique | B116: 8 - Dispositif électrique | C116: 8 - Dispositif électrique | D116: 8.3 | E116: Pose et raccordement d'un para-surstenseur modulaire 275 V | G116: U | H116: 30 | J116: 8.3 · Pose et raccordement d'un para-surstenseur modulaire 275 V | K116: BPU ST VDR Optique · BPU MISSION 3 Optique ligne 103
A117: VDR Optique | B117: 8 - Dispositif électrique | C117: 8 - Dispositif électrique | D117: 8.4 | E117: Pose et raccordement d'une borne type Coffret Haut | F117: - Totalement équipé (dispositifs de protection éléctriques, platines, raccordement, extrémités thermo-retractables comprise et mise à la terre). - De dimension : 495 x 230 x 168 Ce prix comprend aussi la fouille, le massif; la dalle, les tiges de scellements et fourreaux nécessaires au passage des câble | G117: U | H117: 150 | J117: 8.4 · Pose et raccordement d'une borne type Coffret Haut | K117: BPU ST VDR Optique · BPU MISSION 3 Optique ligne 104

Sheet Majorations
A1: Code | B1: Libellé dans le devis | C1: Coefficient | D1: Unité | E1: Commentaire | F1: Source
A2: MC-07 | B2: MC-07 · Technicien supplémentaire | C2: 1.4906176 | D2: coef. appliqué au forfait | E2: Majoration par technicien supplémentaire sur une intervention (à l'acte) | F2: Maintenance BPU ST · BPU ligne 28
A3: MC-08 | B3: MC-08 · Intervention en HNO | C3: 1.4078055 | D3: coef. appliqué au forfait | E3: Majoration en cas d'intervention en HNO (min 20% de l'inter. en HNO) (à l'acte) | F3: Maintenance BPU ST · BPU ligne 29
A5: Le montant de la ligne du devis est multiplié par le coefficient (ex. 1,4078 = +40,78 %).
